pypioffline.py
pypioffline-0.0.1.dist-info/licenses/LICENSE
pypioffline-0.0.1.dist-info/METADATA
pypioffline-0.0.1.dist-info/WHEEL
pypioffline-0.0.1.dist-info/entry_points.txt
pypioffline-0.0.1.dist-info/top_level.txt
pypioffline-0.0.1.dist-info/RECORD
