Metadata-Version: 2.4
Name: pypioffline
Version: 0.0.1
Summary: Create a local pypi repository to use pip offline
Author-email: hippysurfer <hippysurfer+pypioffline@gmail.com>
License-Expression: MIT
Project-URL: Homepage, https://github.com/hippysurfer/pypioffline
Project-URL: Repository, https://github.com/hippysurfer/pypioffline
Keywords: pypioffline,development,pip,mirror,packages,offline,repository
Classifier: Development Status :: 3 - Alpha
Classifier: Intended Audience :: Developers
Classifier: Topic :: Software Development :: Build Tools
Classifier: Programming Language :: Python :: 3.10
Requires-Python: >=3.10
License-File: LICENSE
Requires-Dist: aiohttp
Requires-Dist: aiofiles
Requires-Dist: lxml
Requires-Dist: tqdm
Requires-Dist: wheel-filename
Dynamic: license-file
